[
    {
        "id": "1jc646h3",
        "pair": "ETH-IOTX",
        "exchange": "binance",
        "from": 1732752000000,
        "to": 1732838400000,
        "timestamp": "2024-11-29T01:46:25.352458",
        "settings": {
            "BUY_METHOD": "channelmaestro",
            "SELL_METHOD": "channelmaestro",
            "PERIOD": "1"
        },
        "performance": {
            "ROI": "1.1%",
            "Sharpe ratio": "2.75",
            "Sortino ratio": "236.56",
            "Average pnl %": "1.52%",
            "Volume": "2.62715 ETH"
        }
    },
    {
        "id": "w5fes0ln",
        "pair": "ETH-XLM",
        "exchange": "binance",
        "from": 1732752000000,
        "to": 1732838400000,
        "timestamp": "2024-11-29T01:42:14.030664",
        "settings": {
            "BUY_METHOD": "channelmaestro",
            "SELL_METHOD": "channelmaestro",
            "PERIOD": "1"
        },
        "performance": {
            "ROI": "0.81%",
            "Sharpe ratio": "2.93",
            "Sortino ratio": "169.93",
            "Average pnl %": "1.48%",
            "Volume": "2.598926 ETH"
        }
    },
    {
        "id": "5mwgqof7",
        "pair": "ETH-APT",
        "exchange": "binance",
        "from": 1732752000000,
        "to": 1732838400000,
        "timestamp": "2024-11-29T02:17:36.201818",
        "settings": {
            "BUY_METHOD": "channelmaestro",
            "SELL_METHOD": "channelmaestro",
            "PERIOD": "1"
        },
        "performance": {
            "ROI": "0.8%",
            "Sharpe ratio": "2.81",
            "Sortino ratio": "159.16",
            "Average pnl %": "1.2%",
            "Volume": "2.772044 ETH"
        }
    },
    {
        "id": "0dj1quya",
        "pair": "ETH-GRT",
        "exchange": "binance",
        "from": 1732752000000,
        "to": 1732838400000,
        "timestamp": "2024-11-29T01:45:31.150072",
        "settings": {
            "BUY_METHOD": "channelmaestro",
            "SELL_METHOD": "channelmaestro",
            "PERIOD": "1"
        },
        "performance": {
            "ROI": "0.68%",
            "Sharpe ratio": "2.96",
            "Sortino ratio": "241.2",
            "Average pnl %": "1.7%",
            "Volume": "1.527646 ETH"
        }
    },
    {
        "id": "gw6w2d6v",
        "pair": "ETH-NEAR",
        "exchange": "binance",
        "from": 1732752000000,
        "to": 1732838400000,
        "timestamp": "2024-11-29T01:58:21.832573",
        "settings": {
            "BUY_METHOD": "channelmaestro",
            "SELL_METHOD": "channelmaestro",
            "PERIOD": "1"
        },
        "performance": {
            "ROI": "0.62%",
            "Sharpe ratio": "2.72",
            "Sortino ratio": "138.39",
            "Average pnl %": "1.33%",
            "Volume": "2.534473 ETH"
        }
    },
    {
        "id": "ynx49ffi",
        "pair": "ETH-LRC",
        "exchange": "binance",
        "from": 1732752000000,
        "to": 1732838400000,
        "timestamp": "2024-11-29T02:40:10.542496",
        "settings": {
            "BUY_METHOD": "channelmaestro",
            "SELL_METHOD": "channelmaestro",
            "PERIOD": "1"
        },
        "performance": {
            "ROI": "0.62%",
            "Sharpe ratio": "2.93",
            "Sortino ratio": "146.48",
            "Average pnl %": "1.2%",
            "Volume": "2.302254 ETH"
        }
    },
    {
        "id": "v8plf75n",
        "pair": "ETH-GALA",
        "exchange": "binance",
        "from": 1732752000000,
        "to": 1732838400000,
        "timestamp": "2024-11-29T01:41:31.638361",
        "settings": {
            "BUY_METHOD": "channelmaestro",
            "SELL_METHOD": "channelmaestro",
            "PERIOD": "1"
        },
        "performance": {
            "ROI": "0.6%",
            "Sharpe ratio": "2.91",
            "Sortino ratio": "283.12",
            "Average pnl %": "2.66%",
            "Volume": "1.162389 ETH"
        }
    },
    {
        "id": "bssjmo6o",
        "pair": "ETH-EGLD",
        "exchange": "binance",
        "from": 1732752000000,
        "to": 1732838400000,
        "timestamp": "2024-11-29T02:22:23.746872",
        "settings": {
            "BUY_METHOD": "channelmaestro",
            "SELL_METHOD": "channelmaestro",
            "PERIOD": "1"
        },
        "performance": {
            "ROI": "0.54%",
            "Sharpe ratio": "2.66",
            "Sortino ratio": "114",
            "Average pnl %": "1.01%",
            "Volume": "2.660341 ETH"
        }
    },
    {
        "id": "s9t6j8lm",
        "pair": "ETH-SLP",
        "exchange": "binance",
        "from": 1732752000000,
        "to": 1732838400000,
        "timestamp": "2024-11-29T02:07:12.707364",
        "settings": {
            "BUY_METHOD": "channelmaestro",
            "SELL_METHOD": "channelmaestro",
            "PERIOD": "1"
        },
        "performance": {
            "ROI": "0.45%",
            "Sharpe ratio": "2.97",
            "Sortino ratio": "333.93",
            "Average pnl %": "2.59%",
            "Volume": "0.731236 ETH"
        }
    },
    {
        "id": "av369i4q",
        "pair": "ETH-RUNE",
        "exchange": "binance",
        "from": 1732752000000,
        "to": 1732838400000,
        "timestamp": "2024-11-29T02:21:40.096560",
        "settings": {
            "BUY_METHOD": "channelmaestro",
            "SELL_METHOD": "channelmaestro",
            "PERIOD": "1"
        },
        "performance": {
            "ROI": "0.44%",
            "Sharpe ratio": "4.67",
            "Sortino ratio": "152.18",
            "Average pnl %": "1.39%",
            "Volume": "1.336235 ETH"
        }
    }
]