[
    {
        "id": "83df9fwz",
        "pair": "BTC-TFUEL",
        "exchange": "binance",
        "from": 1725667200000,
        "to": 1726272000000,
        "timestamp": "2024-09-14T03:00:31.544879",
        "settings": {
            "BUY_METHOD": "channelmaestro",
            "SELL_METHOD": "channelmaestro",
            "PERIOD": "5"
        },
        "performance": {
            "ROI": "2.72%",
            "Sharpe ratio": "0.98",
            "Sortino ratio": "47.73",
            "Average pnl %": "1.95%",
            "Volume": "0.275094 BTC"
        }
    },
    {
        "id": "suco307i",
        "pair": "BTC-GALA",
        "exchange": "binance",
        "from": 1725667200000,
        "to": 1726272000000,
        "timestamp": "2024-09-14T02:48:40.013858",
        "settings": {
            "BUY_METHOD": "channelmaestro",
            "SELL_METHOD": "channelmaestro",
            "PERIOD": "5"
        },
        "performance": {
            "ROI": "2.14%",
            "Sharpe ratio": "0.81",
            "Sortino ratio": "198.59",
            "Average pnl %": "3.11%",
            "Volume": "0.195218 BTC"
        }
    },
    {
        "id": "yb6697pk",
        "pair": "BTC-GTC",
        "exchange": "binance",
        "from": 1725667200000,
        "to": 1726272000000,
        "timestamp": "2024-09-14T02:52:55.088300",
        "settings": {
            "BUY_METHOD": "channelmaestro",
            "SELL_METHOD": "channelmaestro",
            "PERIOD": "5"
        },
        "performance": {
            "ROI": "1.99%",
            "Sharpe ratio": "1.2",
            "Sortino ratio": "71.01",
            "Average pnl %": "1.68%",
            "Volume": "0.315875 BTC"
        }
    },
    {
        "id": "3buwfl1z",
        "pair": "BTC-ROSE",
        "exchange": "binance",
        "from": 1725667200000,
        "to": 1726272000000,
        "timestamp": "2024-09-14T03:24:48.883186",
        "settings": {
            "BUY_METHOD": "channelmaestro",
            "SELL_METHOD": "channelmaestro",
            "PERIOD": "5"
        },
        "performance": {
            "ROI": "1.88%",
            "Sharpe ratio": "1.43",
            "Sortino ratio": "10.64",
            "Average pnl %": "1.83%",
            "Volume": "0.238706 BTC"
        }
    },
    {
        "id": "386nbomd",
        "pair": "BTC-SAGA",
        "exchange": "binance",
        "from": 1725667200000,
        "to": 1726272000000,
        "timestamp": "2024-09-14T02:56:44.501596",
        "settings": {
            "BUY_METHOD": "channelmaestro",
            "SELL_METHOD": "channelmaestro",
            "PERIOD": "5"
        },
        "performance": {
            "ROI": "1.81%",
            "Sharpe ratio": "1.31",
            "Sortino ratio": "14.77",
            "Average pnl %": "2.36%",
            "Volume": "0.192769 BTC"
        }
    },
    {
        "id": "5sua51ug",
        "pair": "BTC-DUSK",
        "exchange": "binance",
        "from": 1725667200000,
        "to": 1726272000000,
        "timestamp": "2024-09-14T03:54:43.813537",
        "settings": {
            "BUY_METHOD": "channelmaestro",
            "SELL_METHOD": "channelmaestro",
            "PERIOD": "5"
        },
        "performance": {
            "ROI": "1.81%",
            "Sharpe ratio": "1.22",
            "Sortino ratio": "25.3",
            "Average pnl %": "2.4%",
            "Volume": "0.218025 BTC"
        }
    },
    {
        "id": "xyk036sj",
        "pair": "BTC-GLMR",
        "exchange": "binance",
        "from": 1725667200000,
        "to": 1726272000000,
        "timestamp": "2024-09-14T02:52:38.724207",
        "settings": {
            "BUY_METHOD": "channelmaestro",
            "SELL_METHOD": "channelmaestro",
            "PERIOD": "5"
        },
        "performance": {
            "ROI": "1.64%",
            "Sharpe ratio": "0.87",
            "Sortino ratio": "8.28",
            "Average pnl %": "1.87%",
            "Volume": "0.173297 BTC"
        }
    },
    {
        "id": "ll2r5n60",
        "pair": "BTC-ORDI",
        "exchange": "binance",
        "from": 1725667200000,
        "to": 1726272000000,
        "timestamp": "2024-09-14T03:11:01.013451",
        "settings": {
            "BUY_METHOD": "channelmaestro",
            "SELL_METHOD": "channelmaestro",
            "PERIOD": "5"
        },
        "performance": {
            "ROI": "1.6%",
            "Sharpe ratio": "3.38",
            "Sortino ratio": "55.76",
            "Average pnl %": "1.93%",
            "Volume": "0.179209 BTC"
        }
    },
    {
        "id": "8qooqacw",
        "pair": "BTC-API3",
        "exchange": "binance",
        "from": 1725667200000,
        "to": 1726272000000,
        "timestamp": "2024-09-14T03:29:01.371655",
        "settings": {
            "BUY_METHOD": "channelmaestro",
            "SELL_METHOD": "channelmaestro",
            "PERIOD": "5"
        },
        "performance": {
            "ROI": "1.6%",
            "Sharpe ratio": "1.52",
            "Sortino ratio": "72.81",
            "Average pnl %": "1.81%",
            "Volume": "0.165898 BTC"
        }
    },
    {
        "id": "cnl1gssn",
        "pair": "BTC-TAO",
        "exchange": "binance",
        "from": 1725667200000,
        "to": 1726272000000,
        "timestamp": "2024-09-14T03:04:04.367083",
        "settings": {
            "BUY_METHOD": "channelmaestro",
            "SELL_METHOD": "channelmaestro",
            "PERIOD": "5"
        },
        "performance": {
            "ROI": "1.56%",
            "Sharpe ratio": "1.75",
            "Sortino ratio": "19.44",
            "Average pnl %": "2.1%",
            "Volume": "0.147784 BTC"
        }
    }
]