[
    {
        "id": "nk3quvew",
        "pair": "BTC-EIGEN",
        "exchange": "binance",
        "from": 1732060800000,
        "to": 1732665600000,
        "timestamp": "2024-11-27T05:16:09.626905",
        "settings": {
            "BUY_METHOD": "channelmaestro",
            "SELL_METHOD": "channelmaestro",
            "PERIOD": "5"
        },
        "performance": {
            "ROI": "8.22%",
            "Sharpe ratio": "1.19",
            "Sortino ratio": "64.03",
            "Average pnl %": "4.02%",
            "Volume": "0.369923 BTC"
        }
    },
    {
        "id": "oz40owzc",
        "pair": "BTC-ETHFI",
        "exchange": "binance",
        "from": 1732060800000,
        "to": 1732665600000,
        "timestamp": "2024-11-27T06:13:14.962295",
        "settings": {
            "BUY_METHOD": "channelmaestro",
            "SELL_METHOD": "channelmaestro",
            "PERIOD": "5"
        },
        "performance": {
            "ROI": "7.31%",
            "Sharpe ratio": "1.85",
            "Sortino ratio": "185.62",
            "Average pnl %": "3.84%",
            "Volume": "0.33186 BTC"
        }
    },
    {
        "id": "6mw448n7",
        "pair": "BTC-SEI",
        "exchange": "binance",
        "from": 1732060800000,
        "to": 1732665600000,
        "timestamp": "2024-11-27T05:58:59.323208",
        "settings": {
            "BUY_METHOD": "channelmaestro",
            "SELL_METHOD": "channelmaestro",
            "PERIOD": "5"
        },
        "performance": {
            "ROI": "6.92%",
            "Sharpe ratio": "4.32",
            "Sortino ratio": "125.66",
            "Average pnl %": "3.73%",
            "Volume": "0.295741 BTC"
        }
    },
    {
        "id": "lewb9avd",
        "pair": "BTC-SCR",
        "exchange": "binance",
        "from": 1732060800000,
        "to": 1732665600000,
        "timestamp": "2024-11-27T05:14:29.573192",
        "settings": {
            "BUY_METHOD": "channelmaestro",
            "SELL_METHOD": "channelmaestro",
            "PERIOD": "5"
        },
        "performance": {
            "ROI": "6.83%",
            "Sharpe ratio": "1.42",
            "Sortino ratio": "30.13",
            "Average pnl %": "2.71%",
            "Volume": "0.507209 BTC"
        }
    },
    {
        "id": "cy55hpgy",
        "pair": "BTC-ZRO",
        "exchange": "binance",
        "from": 1732060800000,
        "to": 1732665600000,
        "timestamp": "2024-11-27T06:59:53.051209",
        "settings": {
            "BUY_METHOD": "channelmaestro",
            "SELL_METHOD": "channelmaestro",
            "PERIOD": "5"
        },
        "performance": {
            "ROI": "6.51%",
            "Sharpe ratio": "2.43",
            "Sortino ratio": "88.31",
            "Average pnl %": "2.81%",
            "Volume": "0.275548 BTC"
        }
    },
    {
        "id": "cpgmpek9",
        "pair": "BTC-ZEC",
        "exchange": "binance",
        "from": 1732060800000,
        "to": 1732665600000,
        "timestamp": "2024-11-27T05:07:43.340302",
        "settings": {
            "BUY_METHOD": "channelmaestro",
            "SELL_METHOD": "channelmaestro",
            "PERIOD": "5"
        },
        "performance": {
            "ROI": "6.39%",
            "Sharpe ratio": "1.66",
            "Sortino ratio": "41.75",
            "Average pnl %": "3.72%",
            "Volume": "0.285504 BTC"
        }
    },
    {
        "id": "dtnqspno",
        "pair": "BTC-ENS",
        "exchange": "binance",
        "from": 1732060800000,
        "to": 1732665600000,
        "timestamp": "2024-11-27T06:04:34.667594",
        "settings": {
            "BUY_METHOD": "channelmaestro",
            "SELL_METHOD": "channelmaestro",
            "PERIOD": "5"
        },
        "performance": {
            "ROI": "6.38%",
            "Sharpe ratio": "1.71",
            "Sortino ratio": "30.14",
            "Average pnl %": "2.63%",
            "Volume": "0.416713 BTC"
        }
    },
    {
        "id": "v1bdjynv",
        "pair": "BTC-BB",
        "exchange": "binance",
        "from": 1732060800000,
        "to": 1732665600000,
        "timestamp": "2024-11-27T05:49:58.146357",
        "settings": {
            "BUY_METHOD": "channelmaestro",
            "SELL_METHOD": "channelmaestro",
            "PERIOD": "5"
        },
        "performance": {
            "ROI": "6.18%",
            "Sharpe ratio": "1.49",
            "Sortino ratio": "33.08",
            "Average pnl %": "2.45%",
            "Volume": "0.391716 BTC"
        }
    },
    {
        "id": "wjarf9co",
        "pair": "BTC-TIA",
        "exchange": "binance",
        "from": 1732060800000,
        "to": 1732665600000,
        "timestamp": "2024-11-27T05:23:08.484886",
        "settings": {
            "BUY_METHOD": "channelmaestro",
            "SELL_METHOD": "channelmaestro",
            "PERIOD": "5"
        },
        "performance": {
            "ROI": "5.95%",
            "Sharpe ratio": "2.1",
            "Sortino ratio": "129.22",
            "Average pnl %": "4.39%",
            "Volume": "0.287103 BTC"
        }
    },
    {
        "id": "xf7vina0",
        "pair": "BTC-AVAX",
        "exchange": "binance",
        "from": 1732060800000,
        "to": 1732665600000,
        "timestamp": "2024-11-27T06:19:49.073098",
        "settings": {
            "BUY_METHOD": "channelmaestro",
            "SELL_METHOD": "channelmaestro",
            "PERIOD": "5"
        },
        "performance": {
            "ROI": "5.61%",
            "Sharpe ratio": "2.29",
            "Sortino ratio": "131.65",
            "Average pnl %": "2.43%",
            "Volume": "0.310539 BTC"
        }
    }
]