[
    {
        "id": "44ewy42e",
        "pair": "BTC-ONE",
        "exchange": "binance",
        "from": 1730505600000,
        "to": 1731110400000,
        "timestamp": "2024-11-09T05:26:57.991710",
        "settings": {
            "BUY_METHOD": "channelmaestro",
            "SELL_METHOD": "channelmaestro",
            "PERIOD": "5"
        },
        "performance": {
            "ROI": "9.75%",
            "Sharpe ratio": "1.58",
            "Sortino ratio": "178.91",
            "Average pnl %": "5.14%",
            "Volume": "0.441213 BTC"
        }
    },
    {
        "id": "525p0w9y",
        "pair": "BTC-SLF",
        "exchange": "binance",
        "from": 1730505600000,
        "to": 1731110400000,
        "timestamp": "2024-11-09T05:55:41.363021",
        "settings": {
            "BUY_METHOD": "channelmaestro",
            "SELL_METHOD": "channelmaestro",
            "PERIOD": "5"
        },
        "performance": {
            "ROI": "5.64%",
            "Sharpe ratio": "1.31",
            "Sortino ratio": "15.7",
            "Average pnl %": "2.07%",
            "Volume": "0.326695 BTC"
        }
    },
    {
        "id": "evbw93cv",
        "pair": "BTC-STG",
        "exchange": "binance",
        "from": 1730505600000,
        "to": 1731110400000,
        "timestamp": "2024-11-09T04:39:20.237413",
        "settings": {
            "BUY_METHOD": "channelmaestro",
            "SELL_METHOD": "channelmaestro",
            "PERIOD": "5"
        },
        "performance": {
            "ROI": "4.33%",
            "Sharpe ratio": "0.38",
            "Sortino ratio": "15.88",
            "Average pnl %": "3.31%",
            "Volume": "0.084192 BTC"
        }
    },
    {
        "id": "4ohdhzef",
        "pair": "BTC-GLMR",
        "exchange": "binance",
        "from": 1730505600000,
        "to": 1731110400000,
        "timestamp": "2024-11-09T04:59:24.403945",
        "settings": {
            "BUY_METHOD": "channelmaestro",
            "SELL_METHOD": "channelmaestro",
            "PERIOD": "5"
        },
        "performance": {
            "ROI": "3.81%",
            "Sharpe ratio": "1.56",
            "Sortino ratio": "16.66",
            "Average pnl %": "1.38%",
            "Volume": "0.229165 BTC"
        }
    },
    {
        "id": "w82j1gm5",
        "pair": "BTC-TRU",
        "exchange": "binance",
        "from": 1730505600000,
        "to": 1731110400000,
        "timestamp": "2024-11-09T04:52:49.891149",
        "settings": {
            "BUY_METHOD": "channelmaestro",
            "SELL_METHOD": "channelmaestro",
            "PERIOD": "5"
        },
        "performance": {
            "ROI": "3.7%",
            "Sharpe ratio": "2.28",
            "Sortino ratio": "17.34",
            "Average pnl %": "2.3%",
            "Volume": "0.254377 BTC"
        }
    },
    {
        "id": "aezwpak9",
        "pair": "BTC-OAX",
        "exchange": "binance",
        "from": 1730505600000,
        "to": 1731110400000,
        "timestamp": "2024-11-09T06:27:50.923685",
        "settings": {
            "BUY_METHOD": "channelmaestro",
            "SELL_METHOD": "channelmaestro",
            "PERIOD": "5"
        },
        "performance": {
            "ROI": "3.58%",
            "Sharpe ratio": "1.68",
            "Sortino ratio": "37.77",
            "Average pnl %": "3.75%",
            "Volume": "0.1968 BTC"
        }
    },
    {
        "id": "kd0e7ztn",
        "pair": "BTC-CTK",
        "exchange": "binance",
        "from": 1730505600000,
        "to": 1731110400000,
        "timestamp": "2024-11-09T05:39:35.669138",
        "settings": {
            "BUY_METHOD": "channelmaestro",
            "SELL_METHOD": "channelmaestro",
            "PERIOD": "5"
        },
        "performance": {
            "ROI": "2.83%",
            "Sharpe ratio": "1.78",
            "Sortino ratio": "27.83",
            "Average pnl %": "2.66%",
            "Volume": "0.225591 BTC"
        }
    },
    {
        "id": "o2xxebui",
        "pair": "BTC-MOVR",
        "exchange": "binance",
        "from": 1730505600000,
        "to": 1731110400000,
        "timestamp": "2024-11-09T04:46:30.014457",
        "settings": {
            "BUY_METHOD": "channelmaestro",
            "SELL_METHOD": "channelmaestro",
            "PERIOD": "5"
        },
        "performance": {
            "ROI": "2.67%",
            "Sharpe ratio": "1.22",
            "Sortino ratio": "8.63",
            "Average pnl %": "1.25%",
            "Volume": "0.220959 BTC"
        }
    },
    {
        "id": "bvx1j2uq",
        "pair": "BTC-CAKE",
        "exchange": "binance",
        "from": 1730505600000,
        "to": 1731110400000,
        "timestamp": "2024-11-09T05:33:00.274305",
        "settings": {
            "BUY_METHOD": "channelmaestro",
            "SELL_METHOD": "channelmaestro",
            "PERIOD": "5"
        },
        "performance": {
            "ROI": "2.64%",
            "Sharpe ratio": "0.75",
            "Sortino ratio": "7.94",
            "Average pnl %": "1.34%",
            "Volume": "0.242375 BTC"
        }
    },
    {
        "id": "22801aps",
        "pair": "BTC-AUCTION",
        "exchange": "binance",
        "from": 1730505600000,
        "to": 1731110400000,
        "timestamp": "2024-11-09T05:25:21.883024",
        "settings": {
            "BUY_METHOD": "channelmaestro",
            "SELL_METHOD": "channelmaestro",
            "PERIOD": "5"
        },
        "performance": {
            "ROI": "2.61%",
            "Sharpe ratio": "1.43",
            "Sortino ratio": "8.51",
            "Average pnl %": "1.08%",
            "Volume": "0.290991 BTC"
        }
    }
]