[
    {
        "id": "y4vpd64h",
        "pair": "BTC-HBAR",
        "exchange": "binance",
        "from": 1731196800000,
        "to": 1731801600000,
        "timestamp": "2024-11-17T06:03:40.104977",
        "settings": {
            "BUY_METHOD": "channelmaestro",
            "SELL_METHOD": "channelmaestro",
            "PERIOD": "5"
        },
        "performance": {
            "ROI": "8.37%",
            "Sharpe ratio": "1.3",
            "Sortino ratio": "70.25",
            "Average pnl %": "4.76%",
            "Volume": "0.25897 BTC"
        }
    },
    {
        "id": "u5q1fymg",
        "pair": "BTC-MANA",
        "exchange": "binance",
        "from": 1731196800000,
        "to": 1731801600000,
        "timestamp": "2024-11-17T05:32:34.952928",
        "settings": {
            "BUY_METHOD": "channelmaestro",
            "SELL_METHOD": "channelmaestro",
            "PERIOD": "5"
        },
        "performance": {
            "ROI": "6.92%",
            "Sharpe ratio": "1.81",
            "Sortino ratio": "21.99",
            "Average pnl %": "2.46%",
            "Volume": "0.367756 BTC"
        }
    },
    {
        "id": "yt8k4syz",
        "pair": "BTC-CLV",
        "exchange": "binance",
        "from": 1731196800000,
        "to": 1731801600000,
        "timestamp": "2024-11-17T05:08:12.448718",
        "settings": {
            "BUY_METHOD": "channelmaestro",
            "SELL_METHOD": "channelmaestro",
            "PERIOD": "5"
        },
        "performance": {
            "ROI": "6.07%",
            "Sharpe ratio": "0.96",
            "Sortino ratio": "227.98",
            "Average pnl %": "7.63%",
            "Volume": "0.21419 BTC"
        }
    },
    {
        "id": "7f8l1n1e",
        "pair": "BTC-OM",
        "exchange": "binance",
        "from": 1731196800000,
        "to": 1731801600000,
        "timestamp": "2024-11-17T05:14:54.210531",
        "settings": {
            "BUY_METHOD": "channelmaestro",
            "SELL_METHOD": "channelmaestro",
            "PERIOD": "5"
        },
        "performance": {
            "ROI": "5.05%",
            "Sharpe ratio": "1.43",
            "Sortino ratio": "125.88",
            "Average pnl %": "2.52%",
            "Volume": "0.364199 BTC"
        }
    },
    {
        "id": "79sogfb1",
        "pair": "BTC-XLM",
        "exchange": "binance",
        "from": 1731196800000,
        "to": 1731801600000,
        "timestamp": "2024-11-17T05:14:47.133481",
        "settings": {
            "BUY_METHOD": "channelmaestro",
            "SELL_METHOD": "channelmaestro",
            "PERIOD": "5"
        },
        "performance": {
            "ROI": "4.39%",
            "Sharpe ratio": "1.35",
            "Sortino ratio": "28.38",
            "Average pnl %": "3.3%",
            "Volume": "0.267279 BTC"
        }
    },
    {
        "id": "9max7c76",
        "pair": "BTC-TLM",
        "exchange": "binance",
        "from": 1731196800000,
        "to": 1731801600000,
        "timestamp": "2024-11-17T06:40:35.522501",
        "settings": {
            "BUY_METHOD": "channelmaestro",
            "SELL_METHOD": "channelmaestro",
            "PERIOD": "5"
        },
        "performance": {
            "ROI": "4.24%",
            "Sharpe ratio": "1.39",
            "Sortino ratio": "79.78",
            "Average pnl %": "7.56%",
            "Volume": "0.133305 BTC"
        }
    },
    {
        "id": "2e1921sm",
        "pair": "BTC-TFUEL",
        "exchange": "binance",
        "from": 1731196800000,
        "to": 1731801600000,
        "timestamp": "2024-11-17T05:38:58.985606",
        "settings": {
            "BUY_METHOD": "channelmaestro",
            "SELL_METHOD": "channelmaestro",
            "PERIOD": "5"
        },
        "performance": {
            "ROI": "4.2%",
            "Sharpe ratio": "1.58",
            "Sortino ratio": "80.48",
            "Average pnl %": "1.75%",
            "Volume": "0.368839 BTC"
        }
    },
    {
        "id": "a0qjouqw",
        "pair": "BTC-XRP",
        "exchange": "binance",
        "from": 1731196800000,
        "to": 1731801600000,
        "timestamp": "2024-11-17T05:44:54.996094",
        "settings": {
            "BUY_METHOD": "channelmaestro",
            "SELL_METHOD": "channelmaestro",
            "PERIOD": "5"
        },
        "performance": {
            "ROI": "3.76%",
            "Sharpe ratio": "1.2",
            "Sortino ratio": "96.57",
            "Average pnl %": "2.19%",
            "Volume": "0.413485 BTC"
        }
    },
    {
        "id": "kjh0nnb5",
        "pair": "BTC-DOT",
        "exchange": "binance",
        "from": 1731196800000,
        "to": 1731801600000,
        "timestamp": "2024-11-17T06:21:05.444304",
        "settings": {
            "BUY_METHOD": "channelmaestro",
            "SELL_METHOD": "channelmaestro",
            "PERIOD": "5"
        },
        "performance": {
            "ROI": "3.52%",
            "Sharpe ratio": "1.37",
            "Sortino ratio": "12.6",
            "Average pnl %": "2.25%",
            "Volume": "0.293282 BTC"
        }
    },
    {
        "id": "mkcb2du7",
        "pair": "BTC-VET",
        "exchange": "binance",
        "from": 1731196800000,
        "to": 1731801600000,
        "timestamp": "2024-11-17T05:26:40.664460",
        "settings": {
            "BUY_METHOD": "channelmaestro",
            "SELL_METHOD": "channelmaestro",
            "PERIOD": "5"
        },
        "performance": {
            "ROI": "3.45%",
            "Sharpe ratio": "1.45",
            "Sortino ratio": "96.22",
            "Average pnl %": "3.74%",
            "Volume": "0.215585 BTC"
        }
    }
]