[
    {
        "id": "xbajiqwx",
        "pair": "USDT-NEIRO",
        "exchange": "binance",
        "from": 1730851200000,
        "to": 1731456000000,
        "timestamp": "2024-11-13T11:04:16.611923",
        "settings": {
            "BUY_METHOD": "channelmaestro",
            "SELL_METHOD": "channelmaestro",
            "PERIOD": "5"
        },
        "performance": {
            "ROI": "5.63%",
            "Sharpe ratio": "1.88",
            "Sortino ratio": "57.3",
            "Average pnl %": "5.16%",
            "Volume": "10289.82 USDT"
        }
    },
    {
        "id": "c506m59e",
        "pair": "USDT-TURBO",
        "exchange": "binance",
        "from": 1730851200000,
        "to": 1731456000000,
        "timestamp": "2024-11-13T12:39:47.174613",
        "settings": {
            "BUY_METHOD": "channelmaestro",
            "SELL_METHOD": "channelmaestro",
            "PERIOD": "5"
        },
        "performance": {
            "ROI": "5.12%",
            "Sharpe ratio": "1.18",
            "Sortino ratio": "43.14",
            "Average pnl %": "3.24%",
            "Volume": "19041.05 USDT"
        }
    },
    {
        "id": "6iud6eus",
        "pair": "USDT-WIF",
        "exchange": "binance",
        "from": 1730851200000,
        "to": 1731456000000,
        "timestamp": "2024-11-13T11:11:26.325968",
        "settings": {
            "BUY_METHOD": "channelmaestro",
            "SELL_METHOD": "channelmaestro",
            "PERIOD": "5"
        },
        "performance": {
            "ROI": "4.4%",
            "Sharpe ratio": "1.32",
            "Sortino ratio": "120.14",
            "Average pnl %": "2.84%",
            "Volume": "15933.95 USDT"
        }
    },
    {
        "id": "nltz5wbo",
        "pair": "USDT-SHIB",
        "exchange": "binance",
        "from": 1730851200000,
        "to": 1731456000000,
        "timestamp": "2024-11-13T10:28:44.116760",
        "settings": {
            "BUY_METHOD": "channelmaestro",
            "SELL_METHOD": "channelmaestro",
            "PERIOD": "5"
        },
        "performance": {
            "ROI": "4.06%",
            "Sharpe ratio": "0.95",
            "Sortino ratio": "161.11",
            "Average pnl %": "2.43%",
            "Volume": "14413.34 USDT"
        }
    },
    {
        "id": "7v1aoych",
        "pair": "USDT-WLD",
        "exchange": "binance",
        "from": 1730851200000,
        "to": 1731456000000,
        "timestamp": "2024-11-13T11:40:28.392307",
        "settings": {
            "BUY_METHOD": "channelmaestro",
            "SELL_METHOD": "channelmaestro",
            "PERIOD": "5"
        },
        "performance": {
            "ROI": "3.85%",
            "Sharpe ratio": "1.16",
            "Sortino ratio": "19.61",
            "Average pnl %": "2.72%",
            "Volume": "13500.37 USDT"
        }
    },
    {
        "id": "b4adknlb",
        "pair": "USDT-OP",
        "exchange": "binance",
        "from": 1730851200000,
        "to": 1731456000000,
        "timestamp": "2024-11-13T12:38:59.584273",
        "settings": {
            "BUY_METHOD": "channelmaestro",
            "SELL_METHOD": "channelmaestro",
            "PERIOD": "5"
        },
        "performance": {
            "ROI": "3.85%",
            "Sharpe ratio": "2.01",
            "Sortino ratio": "16.94",
            "Average pnl %": "2.08%",
            "Volume": "19166.69 USDT"
        }
    },
    {
        "id": "e05i24se",
        "pair": "USDT-BONK",
        "exchange": "binance",
        "from": 1730851200000,
        "to": 1731456000000,
        "timestamp": "2024-11-13T10:21:16.102574",
        "settings": {
            "BUY_METHOD": "channelmaestro",
            "SELL_METHOD": "channelmaestro",
            "PERIOD": "5"
        },
        "performance": {
            "ROI": "3.78%",
            "Sharpe ratio": "2.34",
            "Sortino ratio": "22.75",
            "Average pnl %": "3.23%",
            "Volume": "10552.33 USDT"
        }
    },
    {
        "id": "odynpskm",
        "pair": "USDT-PEPE",
        "exchange": "binance",
        "from": 1730851200000,
        "to": 1731456000000,
        "timestamp": "2024-11-13T10:57:20.180965",
        "settings": {
            "BUY_METHOD": "channelmaestro",
            "SELL_METHOD": "channelmaestro",
            "PERIOD": "5"
        },
        "performance": {
            "ROI": "3.77%",
            "Sharpe ratio": "1.06",
            "Sortino ratio": "197.82",
            "Average pnl %": "4.35%",
            "Volume": "8568.97 USDT"
        }
    },
    {
        "id": "l0y7pxq0",
        "pair": "USDT-RUNE",
        "exchange": "binance",
        "from": 1730851200000,
        "to": 1731456000000,
        "timestamp": "2024-11-13T12:46:41.824569",
        "settings": {
            "BUY_METHOD": "channelmaestro",
            "SELL_METHOD": "channelmaestro",
            "PERIOD": "5"
        },
        "performance": {
            "ROI": "3.73%",
            "Sharpe ratio": "1.92",
            "Sortino ratio": "26.26",
            "Average pnl %": "2.79%",
            "Volume": "14749.71 USDT"
        }
    },
    {
        "id": "ufprkepc",
        "pair": "USDT-FLOKI",
        "exchange": "binance",
        "from": 1730851200000,
        "to": 1731456000000,
        "timestamp": "2024-11-13T10:34:02.790027",
        "settings": {
            "BUY_METHOD": "channelmaestro",
            "SELL_METHOD": "channelmaestro",
            "PERIOD": "5"
        },
        "performance": {
            "ROI": "3.54%",
            "Sharpe ratio": "1.45",
            "Sortino ratio": "22.64",
            "Average pnl %": "2.49%",
            "Volume": "13926.01 USDT"
        }
    }
]