[
    {
        "id": "0klxkuom",
        "pair": "BTC-FLUX",
        "exchange": "binance",
        "from": 1724803200000,
        "to": 1725408000000,
        "timestamp": "2024-09-04T04:29:56.846964",
        "settings": {
            "BUY_METHOD": "channelmaestro",
            "SELL_METHOD": "channelmaestro",
            "PERIOD": "5"
        },
        "performance": {
            "ROI": "6.64%",
            "Sharpe ratio": "0.63",
            "Sortino ratio": "23.92",
            "Average pnl %": "4.21%",
            "Volume": "0.120301 BTC"
        }
    },
    {
        "id": "t8rly262",
        "pair": "BTC-IDEX",
        "exchange": "binance",
        "from": 1724803200000,
        "to": 1725408000000,
        "timestamp": "2024-09-04T04:24:14.896690",
        "settings": {
            "BUY_METHOD": "channelmaestro",
            "SELL_METHOD": "channelmaestro",
            "PERIOD": "5"
        },
        "performance": {
            "ROI": "5.72%",
            "Sharpe ratio": "1.41",
            "Sortino ratio": "36.69",
            "Average pnl %": "6.77%",
            "Volume": "0.165797 BTC"
        }
    },
    {
        "id": "1y1naz41",
        "pair": "BTC-APT",
        "exchange": "binance",
        "from": 1724803200000,
        "to": 1725408000000,
        "timestamp": "2024-09-04T05:54:59.767941",
        "settings": {
            "BUY_METHOD": "channelmaestro",
            "SELL_METHOD": "channelmaestro",
            "PERIOD": "5"
        },
        "performance": {
            "ROI": "3.28%",
            "Sharpe ratio": "0.9",
            "Sortino ratio": "142.73",
            "Average pnl %": "2.14%",
            "Volume": "0.350824 BTC"
        }
    },
    {
        "id": "uxqf3y4d",
        "pair": "BTC-SFP",
        "exchange": "binance",
        "from": 1724803200000,
        "to": 1725408000000,
        "timestamp": "2024-09-04T05:21:33.148289",
        "settings": {
            "BUY_METHOD": "channelmaestro",
            "SELL_METHOD": "channelmaestro",
            "PERIOD": "5"
        },
        "performance": {
            "ROI": "3.03%",
            "Sharpe ratio": "1.6",
            "Sortino ratio": "19.18",
            "Average pnl %": "2%",
            "Volume": "0.235894 BTC"
        }
    },
    {
        "id": "wsg6ba8i",
        "pair": "BTC-UMA",
        "exchange": "binance",
        "from": 1724803200000,
        "to": 1725408000000,
        "timestamp": "2024-09-04T05:22:59.618099",
        "settings": {
            "BUY_METHOD": "channelmaestro",
            "SELL_METHOD": "channelmaestro",
            "PERIOD": "5"
        },
        "performance": {
            "ROI": "2.94%",
            "Sharpe ratio": "1.12",
            "Sortino ratio": "126.71",
            "Average pnl %": "0%",
            "Volume": "0.33748 BTC"
        }
    },
    {
        "id": "w9dnn4z1",
        "pair": "BTC-ORDI",
        "exchange": "binance",
        "from": 1724803200000,
        "to": 1725408000000,
        "timestamp": "2024-09-04T06:18:34.134855",
        "settings": {
            "BUY_METHOD": "channelmaestro",
            "SELL_METHOD": "channelmaestro",
            "PERIOD": "5"
        },
        "performance": {
            "ROI": "2.64%",
            "Sharpe ratio": "1.57",
            "Sortino ratio": "10.67",
            "Average pnl %": "1.84%",
            "Volume": "0.253402 BTC"
        }
    },
    {
        "id": "n6ls06y6",
        "pair": "BTC-STRK",
        "exchange": "binance",
        "from": 1724803200000,
        "to": 1725408000000,
        "timestamp": "2024-09-04T05:43:31.023425",
        "settings": {
            "BUY_METHOD": "channelmaestro",
            "SELL_METHOD": "channelmaestro",
            "PERIOD": "5"
        },
        "performance": {
            "ROI": "2.56%",
            "Sharpe ratio": "1.74",
            "Sortino ratio": "76.12",
            "Average pnl %": "1.77%",
            "Volume": "0.32538 BTC"
        }
    },
    {
        "id": "emk7oeiv",
        "pair": "BTC-SUI",
        "exchange": "binance",
        "from": 1724803200000,
        "to": 1725408000000,
        "timestamp": "2024-09-04T04:40:52.559573",
        "settings": {
            "BUY_METHOD": "channelmaestro",
            "SELL_METHOD": "channelmaestro",
            "PERIOD": "5"
        },
        "performance": {
            "ROI": "2.5%",
            "Sharpe ratio": "1.13",
            "Sortino ratio": "51.81",
            "Average pnl %": "1.78%",
            "Volume": "0.380993 BTC"
        }
    },
    {
        "id": "t52o3oug",
        "pair": "BTC-DATA",
        "exchange": "binance",
        "from": 1724803200000,
        "to": 1725408000000,
        "timestamp": "2024-09-04T04:24:10.126700",
        "settings": {
            "BUY_METHOD": "channelmaestro",
            "SELL_METHOD": "channelmaestro",
            "PERIOD": "5"
        },
        "performance": {
            "ROI": "2.34%",
            "Sharpe ratio": "1.37",
            "Sortino ratio": "25.01",
            "Average pnl %": "3.9%",
            "Volume": "0.139232 BTC"
        }
    },
    {
        "id": "fogs0psl",
        "pair": "BTC-BB",
        "exchange": "binance",
        "from": 1724803200000,
        "to": 1725408000000,
        "timestamp": "2024-09-04T05:09:41.304849",
        "settings": {
            "BUY_METHOD": "channelmaestro",
            "SELL_METHOD": "channelmaestro",
            "PERIOD": "5"
        },
        "performance": {
            "ROI": "2.09%",
            "Sharpe ratio": "1.22",
            "Sortino ratio": "93.23",
            "Average pnl %": "1.84%",
            "Volume": "0.262714 BTC"
        }
    }
]